bs_pathutils/__init__.py
bs_pathutils/ensure.py
bs_pathutils-0.1.0.dist-info/LICENSE
bs_pathutils-0.1.0.dist-info/METADATA
bs_pathutils-0.1.0.dist-info/WHEEL
bs_pathutils-0.1.0.dist-info/top_level.txt
bs_pathutils-0.1.0.dist-info/RECORD
